MANIFEST.in
captchaimage.c
setup.py
mycaptcha/__init__.py
mycaptcha/fake_captchaimage.py
mycaptcha/font.ttf
mycaptcha.egg-info/PKG-INFO
mycaptcha.egg-info/SOURCES.txt
mycaptcha.egg-info/dependency_links.txt
mycaptcha.egg-info/not-zip-safe
mycaptcha.egg-info/top_level.txt