Metadata-Version: 1.0
Name: mycaptcha
Version: 1.9
Summary: Create captcha image data
Home-page: UNKNOWN
Author: zsp
Author-email: zsp007@gmail.com
License: Public Domain
Platform: UNKNOWN
Classifier: License :: Public Domain
Classifier: Programming Language :: C
